setup.py
bosrv/BigObjectService.py
bosrv/__init__.py
bosrv/connect.py
bosrv/constants.py
bosrv/request.py
bosrv/ttypes.py
bosrvclient.egg-info/PKG-INFO
bosrvclient.egg-info/SOURCES.txt
bosrvclient.egg-info/dependency_links.txt
bosrvclient.egg-info/not-zip-safe
bosrvclient.egg-info/requires.txt
bosrvclient.egg-info/top_level.txt
exc/__init__.py
exc/constants.py
exc/ttypes.py