Metadata-Version: 1.0
Name: bosrvclient
Version: 0.1.8
Summary: BigObject service client for python
Home-page: https://bitbucket.org/macrodata/bosrvclient-py.git
Author: MacroData Inc
Author-email: info@macrodatalab.com
License: Apache 2.0
Keywords: bigobject,macrodata,analytics
Platform: UNKNOWN
